src/shift_reg.v
module shift_reg #(
    parameter integer N = 8
) (
    input  wire         clk,
    input  wire         reset_n,
    input  wire         enable,
    input  wire         data_in,
    output reg  [N-1:0] data_out
);

    localparam integer CNT_W = (N <= 1) ? 1 : $clog2(N + 1);

    reg [CNT_W-1:0] bit_count;
    reg             locked;

    always @(posedge clk or negedge reset_n) begin
        if (!reset_n) begin
            data_out  <= {N{1'b0}};
            bit_count <= {CNT_W{1'b0}};
            locked    <= 1'b0;
        end else if (enable && !locked) begin
            data_out <= (data_out << 1) | data_in;

            if (bit_count == N-1) begin
                locked <= 1'b1;
            end else begin
                bit_count <= bit_count + 1'b1;
            end
        end
    end

endmodule

tb/tb_shiftreg.sv
`timescale 1ns/1ps

module tb_shift_reg;

    parameter integer N = 8;

    reg             clk;
    reg             reset_n;
    reg             enable;
    reg             data_in;
    wire [N-1:0]    data_out;

    // DUT
    shift_reg #(
        .N(N)
    ) dut (
        .clk(clk),
        .reset_n(reset_n),
        .enable(enable),
        .data_in(data_in),
        .data_out(data_out)
    );

    // Clock: 100 MHz -> 10 ns period
    initial begin
        clk = 1'b0;
        forever #5 clk = ~clk;
    end

    // Dump waveforms
    initial begin
        $dumpfile("./tb/out/shift_reg.vcd");
        $dumpvars(0, tb_shift_reg);
    end

    // Stimulus
    integer i;
    reg [N-1:0] test_pattern;
    reg [N-1:0] expected;

    initial begin
        $display("Starting shift_reg testbench...");

        // Init
        reset_n      = 1'b0;
        enable       = 1'b0;
        data_in      = 1'b0;
        test_pattern = 8'b10110011;
        expected     = {N{1'b0}};

        // Hold reset for a bit
        #20;
        reset_n = 1'b1;
        #10;

        // Shift in N bits, MSB first
        enable = 1'b1;
        for (i = N-1; i >= 0; i = i - 1) begin
            data_in = test_pattern[i];
            @(posedge clk);
            expected = (expected << 1) | test_pattern[i];

            #1;
            $display("time=%0t  data_in=%b  data_out=%b  expected=%b",
                     $time, test_pattern[i], data_out, expected);

            if (data_out !== expected) begin
                $display("ERROR: mismatch at bit %0d: got %b expected %b",
                         i, data_out, expected);
                $stop;
            end
        end

        // Try shifting more after lock, output should stay unchanged
        data_in = 1'b0;
        @(posedge clk);
        #1;
        if (data_out !== test_pattern) begin
            $display("ERROR: data_out changed after lock. got=%b expected=%b",
                     data_out, test_pattern);
            $stop;
        end

        data_in = 1'b1;
        @(posedge clk);
        #1;
        if (data_out !== test_pattern) begin
            $display("ERROR: data_out changed after lock. got=%b expected=%b",
                     data_out, test_pattern);
            $stop;
        end

        $display("Test passed. Final data_out = %b", data_out);
        #20;
        $finish;
    end

endmodule

tb/out/shift_reg_tb.vcd
$date
	Tue Mar 24 22:35:41 2026
$end
$version
	Icarus Verilog
$end
$timescale
	1ps
$end
$scope module tb_shift_reg $end
$var wire 8 ! data_out [7:0] $end
$var parameter 32 " N $end
$var reg 1 # clk $end
$var reg 1 $ data_in $end
$var reg 1 % enable $end
$var reg 8 & expected [7:0] $end
$var reg 1 ' reset_n $end
$var reg 8 ( test_pattern [7:0] $end
$var integer 32 ) i [31:0] $end
$scope module dut $end
$var wire 1 # clk $end
$var wire 1 $ data_in $end
$var wire 1 % enable $end
$var wire 1 ' reset_n $end
$var parameter 32 * CNT_W $end
$var parameter 32 + N $end
$var reg 4 , bit_count [3:0] $end
$var reg 8 - data_out [7:0] $end
$var reg 1 . locked $end
$upscope $end
$upscope $end
$enddefinitions $end
$comment Show the parameter values. $end
$dumpall
b1000 +
b100 *
b1000 "
$end
#0
$dumpvars
0.
b0 -
b0 ,
bx )
b10110011 (
0'
b0 &
0%
0$
0#
b0 !
$end
#5000
1#
#10000
0#
#15000
1#
#20000
0#
1'
#25000
1#
#30000
0#
1$
b111 )
1%
#35000
b1 ,
b1 !
b1 -
b1 &
1#
#36000
0$
b110 )
#40000
0#
#45000
b10 ,
b10 !
b10 -
b10 &
1#
#46000
1$
b101 )
#50000
0#
#55000
b11 ,
b101 !
b101 -
b101 &
1#
#56000
b100 )
#60000
0#
#65000
b100 ,
b1011 !
b1011 -
b1011 &
1#
#66000
0$
b11 )
#70000
0#
#75000
b101 ,
b10110 !
b10110 -
b10110 &
1#
#76000
b10 )
#80000
0#
#85000
b110 ,
b101100 !
b101100 -
b101100 &
1#
#86000
1$
b1 )
#90000
0#
#95000
b111 ,
b1011001 !
b1011001 -
b1011001 &
1#
#96000
b0 )
#100000
0#
#105000
1.
b10110011 !
b10110011 -
b10110011 &
1#
#106000
0$
b11111111111111111111111111111111 )
#110000
0#
#115000
1#
#116000
1$
